[
    {"item": "band collar shirt", "default_color": "white", "gender": "male"},
    {"item": "bath robe", "default_color": "white", "gender": "unisex"},
    {"item": "bikini", "default_color": "black", "gender": "female"},
    {"item": "blazer", "default_color": "navy", "gender": "unisex"},
    {"item": "blouse", "default_color": "cream", "gender": "female"},
    {"item": "bodysuit", "default_color": "nude", "gender": "female"},
    {"item": "boiler suit", "default_color": "olive green", "gender": "unisex"},
    {"item": "bra", "default_color": "white", "gender": "female"},
    {"item": "bralette", "default_color": "pink", "gender": "female"},
    {"item": "business suit", "default_color": "black", "gender": "unisex"},    
    {"item": "bustier top", "default_color": "burgundy", "gender": "female"},
    {"item": "button-up dress", "default_color": "blue", "gender": "female"},
    {"item": "catsuit", "default_color": "black", "gender": "female"},
    {"item": "cable knit sweater", "default_color": "cream", "gender": "unisex"},
    {"item": "camisole", "default_color": "nude", "gender": "female"},
    {"item": "cardigan", "default_color": "beige", "gender": "unisex"},
    {"item": "cheongsam", "default_color": "floral multi-colored", "gender": "female"},    
    {"item": "corset top", "default_color": "black", "gender": "female"},
    {"item": "corset", "default_color": "red", "gender": "female"},
    {"item": "crochet dress", "default_color": "white", "gender": "female"},
    {"item": "crochet top", "default_color": "ivory", "gender": "female"},
    {"item": "crocheted bikini", "default_color": "multi", "gender": "female"},
    {"item": "crop-top", "default_color": "black", "gender": "female"},
    {"item": "cropped shirt", "default_color": "blue", "gender": "unisex"},
    {"item": "cropped t-shirt", "default_color": "grey", "gender": "unisex"},
    {"item": "cupless bra", "default_color": "black", "gender": "female"},
    {"item": "cut-out dress", "default_color": "black", "gender": "female"},
    {"item": "deep v-neck top", "default_color": "black", "gender": "female"},
    {"item": "denim jacket", "default_color": "blue", "gender": "unisex"},
    {"item": "dress", "default_color": "red", "gender": "female"},
    {"item": "dress, sleeveless, v-neckline", "default_color": "navy", "gender": "female"},
    {"item": "flannel shirt", "default_color": "plaid", "gender": "unisex"},
    {"item": "floral dress", "default_color": "multi-colored", "gender": "female"},
    {"item": "fur-lined hood", "default_color": "grey", "gender": "unisex"},
    {"item": "fur coat", "default_color": "cream", "gender": "female"},
    {"item": "graphic t-shirt", "default_color": "multi", "gender": "unisex"},
    {"item": "halter dress", "default_color": "red", "gender": "female"},
    {"item": "halter top", "default_color": "black", "gender": "female"},
    {"item": "henley shirt", "default_color": "maroon", "gender": "unisex"},
    {"item": "hoodie", "default_color": "maroon", "gender": "unisex"},
    {"item": "jacket", "default_color": "black", "gender": "unisex"},
    {"item": "jumpsuit", "default_color": "black", "gender": "female"},
    {"item": "kimono", "default_color": "deep purple", "gender": "unisex"},
    {"item": "lace dress", "default_color": "white", "gender": "female"},
    {"item": "lace lingerie", "default_color": "black", "gender": "female"},
    {"item": "lace top", "default_color": "white", "gender": "female"},
    {"item": "lace-up top", "default_color": "black", "gender": "female"},
    {"item": "latex bodysuit", "default_color": "black", "gender": "female"},
    {"item": "leotard", "default_color": "white", "gender": "female"},
    {"item": "leather dress", "default_color": "black", "gender": "female"},
    {"item": "long-sleeve dress", "default_color": "blue", "gender": "female"},
    {"item": "long-sleeve top", "default_color": "grey", "gender": "unisex"},
    {"item": "maxi dress", "default_color": "floral pattern", "gender": "female"},
    {"item": "mesh top", "default_color": "black", "gender": "female"},
    {"item": "muscle shirt", "default_color": "black", "gender": "male"},
    {"item": "one-piece swimsuit", "default_color": "metallic silver", "gender": "female"},
    {"item": "overshirt", "default_color": "olive green", "gender": "unisex"},    
    {"item": "peasant blouse", "default_color": "white", "gender": "female"},
    {"item": "peephole bra", "default_color": "black", "gender": "female"},
    {"item": "peplum top", "default_color": "red", "gender": "female"},
    {"item": "polo shirt", "default_color": "navy", "gender": "unisex"},
    {"item": "poncho", "default_color": "tan", "gender": "unisex"},
    {"item": "post-apocalyptic jacket", "default_color": "yellow", "gender": "unisex"},
    {"item": "romper", "default_color": "light blue", "gender": "female"},
    {"item": "sequin top", "default_color": "silver", "gender": "female"},
    {"item": "sheath dress", "default_color": "black", "gender": "female"},
    {"item": "shell top", "default_color": "black", "gender": "female"},
    {"item": "shift dress", "default_color": "royal blue", "gender": "female"},
    {"item": "sports bra", "default_color": "grey", "gender": "female"},
    {"item": "sweatshirt", "default_color": "grey", "gender": "unisex"},
    {"item": "tank top", "default_color": "white", "gender": "unisex"},
    {"item": "top", "default_color": "black", "gender": "unisex"},
    {"item": "turtleneck", "default_color": "charcoal", "gender": "unisex"},
    {"item": "uniform shirt", "default_color": "dark blue", "gender": "unisex"},
    {"item": "wrap dress", "default_color": "emerald green", "gender": "female"},
    {"item": "yukata", "default_color": "floral multi-colored", "gender": "female"}
]
